readkeys/__init__.py
readkeys/getch_unix.py
readkeys/getch_windows.py
readkeys/readkeys.py
readkeys-1.0.2.dist-info/LICENSE
readkeys-1.0.2.dist-info/WHEEL
readkeys-1.0.2.dist-info/METADATA
readkeys-1.0.2.dist-info/RECORD
