Metadata-Version: 2.1
Name: readkeys
Version: 1.0.2
Summary: Python library to read from stdin a single char, keypress (with escape sequences) or line.
Home-page: https://gitlab.com/MatteoCampinoti94/PythonRead
License: EUPL-1.2
Author: Matteo Campinoti
Author-email: matteo.campinoti94@gmail.com
Requires-Python: >=3.8,<4.0
Classifier: Development Status :: 5 - Production/Stable
Classifier: Intended Audience :: Developers
Classifier: License :: OSI Approved :: European Union Public Licence 1.2 (EUPL 1.2)
Classifier: Operating System :: OS Independent
Classifier: Programming Language :: Python :: 3
Classifier: Programming Language :: Python :: 3.8
Classifier: Programming Language :: Python :: 3.9
Classifier: Topic :: Software Development :: Libraries
Project-URL: Repository, https://gitlab.com/MatteoCampinoti94/PythonRead
